genialntools/__init__.py
genialntools/genial.py
genialntools-3.0.0.dist-info/METADATA
genialntools-3.0.0.dist-info/WHEEL
genialntools-3.0.0.dist-info/top_level.txt
genialntools-3.0.0.dist-info/RECORD
